rootwater/__init__.py
rootwater/gebauer_params.py
rootwater/rootwater.py
rootwater/sapflow.py
rootwater/tests/__init__.py
rootwater/tests/core.py
rootwater-0.3.dist-info/LICENSE
rootwater-0.3.dist-info/METADATA
rootwater-0.3.dist-info/WHEEL
rootwater-0.3.dist-info/top_level.txt
rootwater-0.3.dist-info/RECORD
