Metadata-Version: 2.1
Name: rootwater
Version: 0.3
Summary: Python package to estimate root water uptake (RWU) from rhizosphere soil moisture dynamics and some tools to handle sap flow measurements
Home-page: https://github.com/cojacoo/rootwater
Author: Conrad Jackisch
Author-email: conrad.jackisch@tbt.tu-freiberg.de
License: MIT
Platform: UNKNOWN
Classifier: Programming Language :: Python :: 3
Classifier: License :: OSI Approved :: MIT License
Classifier: Operating System :: OS Independent
Requires-Dist: numpy
Requires-Dist: pandas
Requires-Dist: nose
Requires-Dist: scipy
Requires-Dist: statsmodels
Requires-Dist: astral (>=2.0)
Requires-Dist: hydroeval
Requires-Dist: sphinx (>=1.4)
Requires-Dist: ipykernel
Requires-Dist: nbsphinx
